BeginnersbookServletJiaochengChuyi/README.md
BeginnersbookServletJiaochengChuyi/__init__.py
BeginnersbookServletJiaochengChuyi/__main__.py
BeginnersbookServletJiaochengChuyi/file.epub
BeginnersbookServletJiaochengChuyi/index.html
BeginnersbookServletJiaochengChuyi/css/__init__.py
BeginnersbookServletJiaochengChuyi/css/annotations.css
BeginnersbookServletJiaochengChuyi/css/main.css
BeginnersbookServletJiaochengChuyi/css/normalize.css
BeginnersbookServletJiaochengChuyi/css/popup.css
BeginnersbookServletJiaochengChuyi/font/__init__.py
BeginnersbookServletJiaochengChuyi/font/fontello.eot
BeginnersbookServletJiaochengChuyi/font/fontello.svg
BeginnersbookServletJiaochengChuyi/font/fontello.ttf
BeginnersbookServletJiaochengChuyi/font/fontello.woff
BeginnersbookServletJiaochengChuyi/img/__init__.py
BeginnersbookServletJiaochengChuyi/img/annotator-glyph-sprite.png
BeginnersbookServletJiaochengChuyi/img/annotator-icon-sprite.png
BeginnersbookServletJiaochengChuyi/img/apple-touch-icon.png
BeginnersbookServletJiaochengChuyi/img/cancelfullscreen.png
BeginnersbookServletJiaochengChuyi/img/close.png
BeginnersbookServletJiaochengChuyi/img/fullscreen.png
BeginnersbookServletJiaochengChuyi/img/loader.gif
BeginnersbookServletJiaochengChuyi/img/menu-icon.png
BeginnersbookServletJiaochengChuyi/img/save.png
BeginnersbookServletJiaochengChuyi/img/saved.png
BeginnersbookServletJiaochengChuyi/img/settings-s.png
BeginnersbookServletJiaochengChuyi/img/settings.png
BeginnersbookServletJiaochengChuyi/img/star.png
BeginnersbookServletJiaochengChuyi/js/__init__.py
BeginnersbookServletJiaochengChuyi/js/epub.js
BeginnersbookServletJiaochengChuyi/js/epub.min.js
BeginnersbookServletJiaochengChuyi/js/epub.min.map
BeginnersbookServletJiaochengChuyi/js/hooks.min.js
BeginnersbookServletJiaochengChuyi/js/hooks.min.map
BeginnersbookServletJiaochengChuyi/js/reader.js
BeginnersbookServletJiaochengChuyi/js/reader.js.map
BeginnersbookServletJiaochengChuyi/js/reader.min.js
beginnersbook_servlet_jiaocheng_chuyi-2024.3.5.0.dist-info/METADATA
beginnersbook_servlet_jiaocheng_chuyi-2024.3.5.0.dist-info/WHEEL
beginnersbook_servlet_jiaocheng_chuyi-2024.3.5.0.dist-info/entry_points.txt
beginnersbook_servlet_jiaocheng_chuyi-2024.3.5.0.dist-info/top_level.txt
beginnersbook_servlet_jiaocheng_chuyi-2024.3.5.0.dist-info/RECORD
